LICENSE
README.md
setup.cfg
setup.py
lasertools_traceretrieve/__init__.py
lasertools_traceretrieve/retriever.py
lasertools_traceretrieve.egg-info/PKG-INFO
lasertools_traceretrieve.egg-info/SOURCES.txt
lasertools_traceretrieve.egg-info/dependency_links.txt
lasertools_traceretrieve.egg-info/requires.txt
lasertools_traceretrieve.egg-info/top_level.txt
lasertools_traceretrieve/algorithm/__init__.py
lasertools_traceretrieve/algorithm/descend.py
lasertools_traceretrieve/resources/__init__.py
lasertools_traceretrieve/resources/colormap_jetwhite.py
lasertools_traceretrieve/resources/retrieve_plot_live.py